README.md
setup.py
autobahn_autoreconnect/__init__.py
autobahn_autoreconnect.egg-info/PKG-INFO
autobahn_autoreconnect.egg-info/SOURCES.txt
autobahn_autoreconnect.egg-info/dependency_links.txt
autobahn_autoreconnect.egg-info/requires.txt
autobahn_autoreconnect.egg-info/top_level.txt