Metadata-Version: 1.0
Name: autobahn-autoreconnect
Version: 0.1.1
Summary: Python Autobahn runner with auto-reconnect feature
Home-page: https://github.com/isra17/autobahn-autoreconnect
Author: isra17
Author-email: isra017@gmail.com
License: LGPL2
Platform: UNKNOWN
